serialization_plugin/__init__.py
serialization_plugin/exceptions.py
serialization_plugin/json_serializer.py
serialization_plugin/serializer.py
serialization_plugin/xml_serializer.py
serialization_plugin-0.1.0.dist-info/METADATA
serialization_plugin-0.1.0.dist-info/WHEEL
serialization_plugin-0.1.0.dist-info/top_level.txt
serialization_plugin-0.1.0.dist-info/RECORD
