Metadata-Version: 2.1
Name: serialization-plugin
Version: 0.1.0
Summary: A plugin for serialization/deserialization in JSON and XML formats
Home-page: https://github.com/BelostotskyNikita/serialization-plugin
Author: Your Name
Author-email: your.email@example.com
Classifier: Programming Language :: Python :: 3
Classifier: License :: OSI Approved :: MIT License
Classifier: Operating System :: OS Independent
Requires-Python: >=3.6
Requires-Dist: dicttoxml >=1.7.4
